{"/*":["X-Frame-Options: DENY","X-XSS-Protection: 1; mode=block","X-Content-Type-Options: nosniff","Referrer-Policy: same-origin"],"/component---src-lekoarts-gatsby-theme-cara-templates-cara-tsx-0f89c884508446f9a7e9.js":["Cache-Control: public, max-age=31536000, immutable"],"/component---cache-caches-gatsby-plugin-offline-app-shell-js-19245c8506e49b502b12.js":["Cache-Control: public, max-age=31536000, immutable"],"/webpack-runtime-66b4b5e6681cea838105.js":["Cache-Control: public, max-age=31536000, immutable"],"/framework-06f646d936b841f99ebd.js":["Cache-Control: public, max-age=31536000, immutable"],"/app-e9e786a51bc293e8c2e2.js":["Cache-Control: public, max-age=31536000, immutable"],"/static/*":["Cache-Control: public, max-age=31536000, immutable"],"/sw.js":["Cache-Control: public, max-age=0, must-revalidate"],"/":["Link: </webpack-runtime-66b4b5e6681cea838105.js>; rel=preload; as=script; nopush","Link: </framework-06f646d936b841f99ebd.js>; rel=preload; as=script; nopush","Link: </app-e9e786a51bc293e8c2e2.js>; rel=preload; as=script; nopush","Link: </component---src-lekoarts-gatsby-theme-cara-templates-cara-tsx-0f89c884508446f9a7e9.js>; rel=preload; as=script; nopush","Link: </page-data/app-data.json>; rel=preload; as=fetch; crossorigin; nopush","Link: </page-data/index/page-data.json>; rel=preload; as=fetch; crossorigin; nopush"],"/offline-plugin-app-shell-fallback/":["Link: </webpack-runtime-66b4b5e6681cea838105.js>; rel=preload; as=script; nopush","Link: </framework-06f646d936b841f99ebd.js>; rel=preload; as=script; nopush","Link: </app-e9e786a51bc293e8c2e2.js>; rel=preload; as=script; nopush","Link: </component---cache-caches-gatsby-plugin-offline-app-shell-js-19245c8506e49b502b12.js>; rel=preload; as=script; nopush","Link: </page-data/app-data.json>; rel=preload; as=fetch; crossorigin; nopush","Link: </page-data/offline-plugin-app-shell-fallback/page-data.json>; rel=preload; as=fetch; crossorigin; nopush"]}